metview/__init__.py
metview/__main__.py
metview/bindings.py
metview/compat.py
metview/dataset.py
metview/gallery.py
metview/layout.py
metview/metview.h
metview/plotting.py
metview/scaling.py
metview/style.py
metview/title.py
metview/track.py
metview/ui.py
metview/etc/areas.yaml
metview/etc/dataset_template.yaml
metview/etc/map_styles.yaml
metview/etc/map_styles_template.yaml
metview/etc/param_styles.yaml
metview/etc/params.yaml
metview/etc/scaling_ecmwf.yaml
metview/etc/units-rules.json
metview/metviewpy/__init__.py
metview/metviewpy/fieldset.py
metview/metviewpy/indexdb.py
metview/metviewpy/indexer.py
metview/metviewpy/ipython.py
metview/metviewpy/maths.py
metview/metviewpy/param.py
metview/metviewpy/temporary.py
metview/metviewpy/utils.py
tests/__init__.py
tests/all_missing_vals.grib
tests/args.py
tests/daily_clims.grib
tests/flextra_output.txt
tests/geo_ncols_8.gpt
tests/geopointset_1.gpts
tests/ml_data.grib
tests/monthly_avg.grib
tests/obs_3day.bufr
tests/rgg_small_subarea_cellarea_ref.grib
tests/sample.csv
tests/sample_metadata.csv
tests/small_odb.odb
tests/t2m_3day.gpt
tests/t_for_xs.grib
tests/t_time_series.grib
tests/t_with_missing.grib
tests/temp_u.odb
tests/test.grib
tests/test_bindings.py
tests/test_dataset.py
tests/test_indexer.py
tests/test_metview.py
tests/test_pp_metview.py
tests/test_style.py
tests/test_utils.py
tests/tuv_pl.grib
tests/uv.gpt
tests/xs_date_mv5.nc
tests/xyv.gpt
tests/zt_multi_expvers.grib
tests/ztu_multi_dim.grib
tests/ds/an/10u_sfc.grib
tests/ds/an/10v_sfc.grib
tests/ds/an/msl_sfc.grib
tests/ds/an/pv_pt.grib
tests/ds/an/t_pl.grib
tests/ds/an/u_pl.grib
tests/ds/an/v_pl.grib
tests/ds/an/w_pl.grib
tests/ds/oper/10u_sfc.grib
tests/ds/oper/10v_sfc.grib
tests/ds/oper/msl_sfc.grib
tests/ds/oper/pv_pt.grib
tests/ds/oper/t_pl.grib
tests/ds/oper/tp_sfc.grib
tests/ds/oper/u_pl.grib
tests/ds/oper/v_pl.grib
tests/ds/oper/w_pl.grib
tests/sort/sort_data.grib
metview-1.16.2.dist-info/AUTHORS.rst
metview-1.16.2.dist-info/LICENSE
metview-1.16.2.dist-info/METADATA
metview-1.16.2.dist-info/WHEEL
metview-1.16.2.dist-info/top_level.txt
metview-1.16.2.dist-info/zip-safe
metview-1.16.2.dist-info/RECORD
